[
    {   "id":"1",
        "img"  : "https://photorankmedia-a.akamaihd.net/media/y/c/k/ycknbc5/normal.jpg",
      
        "title" :" @jackiecelna"
    }, 
    { "id":"2"  ,
        "img"  : "https://photorankmedia-a.akamaihd.net/media/u/z/w/uzwv7c5/normal.jpg",
        "title" :"@faithfullyexplorng"
    },
    {    "id":"3",
        "img"  :"https://photorankmedia-a.akamaihd.net/media/e/6/5/e65s7c5/normal.jpg",
        
       
        "title" :"@bailey.xo.lane"
    },
    {    "id":"4",
        "img"  : "https://z3photorankmedia-a.akamaihd.net/media/s/5/w/s5w69c5/normal.jpg",
       
        "title" :"@dixie_3"
    },
    {    "id":"5",
        "img"  :"https://z1photorankmedia-a.akamaihd.net/media/d/j/b/djbbbc5/normal.jpg",
        "title" : "@faithfullyexplorng" 
    }
]
